task2md/__init__.py
task2md/task2md.py
task2md/template/__init__.py
task2md/template/file.py
task2md/template/header.py
task2md/template/index.py
task2md/template/task.py
task2md/template/variable.py
task2md/util/__init__.py
task2md/util/dir.py
task2md-1.1.2.dist-info/METADATA
task2md-1.1.2.dist-info/WHEEL
task2md-1.1.2.dist-info/entry_points.txt
task2md-1.1.2.dist-info/licenses/LICENSE
task2md-1.1.2.dist-info/RECORD
