Metadata-Version: 2.3
Name: task2md
Version: 1.1.2
Summary: A program to generate markdown documentation files from Task files
Project-URL: Homepage, https://gitlab.com/op_so/task/task2md
Project-URL: Documentation, https://op_so.gitlab.io/task/task2md/
Author-email: FX Soubirou <soubirou@yahoo.fr>
License: MIT
License-File: LICENSE
Classifier: License :: OSI Approved :: MIT License
Classifier: Operating System :: OS Independent
Classifier: Programming Language :: Python :: 3
Requires-Python: >=3.10
Requires-Dist: click>=8.1.7
Requires-Dist: pydantic>=2.6.3
Requires-Dist: pyyaml>=6.0.1
Requires-Dist: types-pyyaml>=6.0.12.12
